{
  "tasklist": [
    {
      "description": "seek approval for payments ",
      "isDone": false,
      "type": "T"
    },
    {
      "description": "meet with Mr Lim ",
      "isDone": true,
      "type": "T"
    },
    {
      "description": "read the forms ",
      "isDone": false,
      "type": "T"
    },
    {
      "description": "Submit application for approval ",
      "isDone": true,
      "type": "D",
      "date": "Nov 11, 2019, 12:00:00 AM"
    },
    {
      "description": "buy food for welcome tea ",
      "isDone": false,
      "type": "D",
      "date": "Nov 17, 2019, 12:00:00 AM"
    },
    {
      "description": "Apply for extra fund ",
      "isDone": false,
      "type": "D",
      "date": "Nov 21, 2019, 12:00:00 AM"
    },
    {
      "description": "Deadlie 4 ",
      "isDone": false,
      "type": "D",
      "date": "Nov 19, 2019, 12:00:00 AM"
    },
    {
      "description": "Todo 4 ",
      "isDone": false,
      "type": "T"
    },
    {
      "description": "Deadline 5  ",
      "isDone": false,
      "type": "D",
      "date": "Nov 11, 2019, 12:00:00 AM"
    },
    {
      "description": "Todo 5 ",
      "isDone": true,
      "type": "T"
    }
  ]
}