{
  "orders": [
    {
      "id": 1571988631278,
      "creationDate": "2019-10-25T07:30:31.278+0000",
      "name": "customer",
      "contact": "N/A",
      "remarks": "N/A",
      "deliveryDate": "2019-10-25T07:30:30.375+0000",
      "status": "ACTIVE",
      "total": 0.0,
      "items": []
    },
    {
      "id": 1571990487857,
      "creationDate": "2019-10-25T08:01:27.857+0000",
      "name": "customer",
      "contact": "N/A",
      "remarks": "N/A",
      "deliveryDate": "1999-10-09T10:00:00.000+0000",
      "status": "ACTIVE",
      "total": 0.0,
      "items": []
    },
    {
      "id": 1571996639843,
      "creationDate": "2019-10-25T09:43:59.843+0000",
      "name": "-contact",
      "contact": "N/A",
      "remarks": "N/A",
      "deliveryDate": "2019-10-25T09:43:53.250+0000",
      "status": "ACTIVE",
      "total": 0.0,
      "items": []
    }
  ],
  "products": [
    {
      "productName": "1",
      "ingredientItems": [
        {
          "ingredient": {
            "name": "ho",
            "unitPrice": 0.0,
            "remarks": "-"
          },
          "amount": 1.1
        }
      ],
      "ingredientCost": 0.0,
      "retailPrice": 0.0,
      "status": "ACTIVE"
    },
    {
      "productName": "2",
      "ingredientItems": [
        {
          "ingredient": {
            "name": "ho",
            "unitPrice": 0.0,
            "remarks": "-"
          },
          "amount": 1.1
        }
      ],
      "ingredientCost": 0.0,
      "retailPrice": 0.0,
      "status": "ACTIVE"
    }
  ],
  "inventory" : [ {
    "ingredient" : {
      "name" : "Coca cola",
      "unitPrice" : 0.0,
      "remarks" : "in cartons"
    },
    "amount" : 10.0
  }, {
    "ingredient" : {
      "name" : "Milk",
      "unitPrice" : 10.0,
      "remarks" : ""
    },
    "amount" : 20.0
  }, {
    "ingredient" : {
      "name" : "Cake",
      "unitPrice" : 5.56,
      "remarks" : ""
    },
    "amount" : 17.5
  }, {
    "ingredient" : {
      "name" : "Fish",
      "unitPrice" : 9.95,
      "remarks" : ""
    },
    "amount" : 10.0
  },
    {
      "ingredient": {
        "name": "Beef",
        "unitPrice": 0.0,
        "remarks": ""
      },
      "amount": 100000.0
    },
    {
      "ingredient": {
        "name": "ho",
        "unitPrice": 0.0,
        "remarks": "-"
      },
      "amount": 0.0
    },
    {
      "ingredient": {
        "name": "-qty",
        "unitPrice": 0.0,
        "remarks": ""
      },
      "amount": 0.0
  } ],
  "shoppingList" : [ {
    "ingredient" : {
      "name" : "Fish",
      "unitPrice" : 9.95,
      "remarks" : ""
    },
    "amount" : 9.0
  }, {
    "ingredient" : {
      "name" : "Chicken",
      "unitPrice" : 5.0,
      "remarks" : ""
    },
    "amount" : 5.0
  }, {
    "ingredient" : {
      "name" : "Pork",
      "unitPrice" : 4.58,
      "remarks" : ""
    },
    "amount" : 6.0
  }, {
    "ingredient" : {
      "name" : "Sotong",
      "unitPrice" : 1.25,
      "remarks" : ""
    },
    "amount" : 5.0
  }, {
    "ingredient" : {
      "name" : "Bread",
      "unitPrice" : 0.0,
      "remarks" : ""
    },
    "amount" : 0.0
  }, {
    "ingredient" : {
      "name" : "Mushroom",
      "unitPrice" : 0.0,
      "remarks" : ""
    },
    "amount" : 5.0
  } ],
  "sales" : [ ],
  "shortcuts" : [ ]
}