{
  "orders" : [ ],
  "products" : [ {
    "productName" : "l",
    "ingredientItems" : [ {
      "ingredient" : {
        "name" : "Cheese",
        "unitPrice" : 0.0,
        "remarks" : "-"
      },
      "amount" : 1.1
    }, {
      "ingredient" : {
        "name" : "Chicken",
        "unitPrice" : 0.0,
        "remarks" : "-"
      },
      "amount" : 1.0
    }, {
      "ingredient" : {
        "name" : "Hello",
        "unitPrice" : 0.0,
        "remarks" : "-"
      },
      "amount" : 2.0
    } ],
    "ingredientCost" : 0.0,
    "retailPrice" : 5.5,
    "status" : "ACTIVE"
  }, {
    "productName" : "llll",
    "ingredientItems" : [ {
      "ingredient" : {
        "name" : "Cheese",
        "unitPrice" : 0.0,
        "remarks" : "-"
      },
      "amount" : 1.1
    }, {
      "ingredient" : {
        "name" : "Chicken",
        "unitPrice" : 0.0,
        "remarks" : "-"
      },
      "amount" : 1.0
    }, {
      "ingredient" : {
        "name" : "Hello",
        "unitPrice" : 0.0,
        "remarks" : "-"
      },
      "amount" : 2.0
    } ],
    "ingredientCost" : 0.0,
    "retailPrice" : 5.5,
    "status" : "ACTIVE"
  }, {
    "productName" : "lll",
    "ingredientItems" : [ {
      "ingredient" : {
        "name" : "Cheese",
        "unitPrice" : 0.0,
        "remarks" : "-"
      },
      "amount" : 1.1
    }, {
      "ingredient" : {
        "name" : "Chicken",
        "unitPrice" : 0.0,
        "remarks" : "-"
      },
      "amount" : 1.0
    }, {
      "ingredient" : {
        "name" : "Hello",
        "unitPrice" : 0.0,
        "remarks" : "-"
      },
      "amount" : 2.0
    } ],
    "ingredientCost" : 0.0,
    "retailPrice" : 5.5,
    "status" : "ACTIVE"
  }, {
    "productName" : "name",
    "ingredientItems" : [ ],
    "ingredientCost" : 0.0,
    "retailPrice" : 0.0,
    "status" : "ACTIVE"
  } ],
  "inventory" : [ {
    "ingredient" : {
      "name" : "Butter",
      "unitPrice" : 5.0,
      "remarks" : ""
    },
    "amount" : 11.0
  }, {
    "ingredient" : {
      "name" : "Cheese",
      "unitPrice" : 0.0,
      "remarks" : "-"
    },
    "amount" : 0.0
  }, {
    "ingredient" : {
      "name" : "Chicken",
      "unitPrice" : 0.0,
      "remarks" : "-"
    },
    "amount" : 0.0
  }, {
    "ingredient" : {
      "name" : "Hello",
      "unitPrice" : 0.0,
      "remarks" : "-"
    },
    "amount" : 0.0
  } ],
  "shoppingList" : [ {
    "ingredient" : {
      "name" : "Flour",
      "unitPrice" : 5.0,
      "remarks" : ""
    },
    "amount" : 5.0
  }, {
    "ingredient" : {
      "name" : "Butter",
      "unitPrice" : 5.0,
      "remarks" : ""
    },
    "amount" : 0.0
  } ],
  "sales" : [ {
    "id" : 1572062704791,
    "description" : "Ingredients purchased.",
    "saleDate" : "2019-10-26T04:05:04.787+0000",
    "value" : 5.0,
    "remarks" : "Ingredients are: -Butter "
  } ],
  "shortcuts" : [ ]
}